psastats/__init__.py
psastats-0.0.1.dist-info/METADATA
psastats-0.0.1.dist-info/WHEEL
psastats-0.0.1.dist-info/license
psastats-0.0.1.dist-info/top_level.txt
psastats-0.0.1.dist-info/RECORD
