Metadata-Version: 2.1
Name: psastats
Version: 0.0.1
Summary: Template to register pypi.
Keywords: system,file,time
Classifier: Programming Language :: Python :: 3
Classifier: Operating System :: OS Independent
Requires-Python: >=3.10
License-File: license
Requires-Dist: numpy
Requires-Dist: pandas
Requires-Dist: openpyxl
Requires-Dist: distributed
